flask_extra/__init__.py
flask_extra/services/__init__.py
flask_extra/services/auth/__init__.py
flask_extra/services/sessions/__init__.py
flask_extra/services/sessions/_models.py
flask_extra/services/sessions/_service.py
flask_extra/services/sessions/tests.py
flask_extra/sqla/__init__.py
flask_extra/sqla/base.py
flask_extra/sqla/repository.py
flask_extra-0.1.1.dist-info/LICENSE
flask_extra-0.1.1.dist-info/METADATA
flask_extra-0.1.1.dist-info/WHEEL
flask_extra-0.1.1.dist-info/RECORD
